datapipelabcustomprocessor/__init__.py
datapipelabcustomprocessor/app/__init__.py
datapipelabcustomprocessor/app/node/__init__.py
datapipelabcustomprocessor/app/node/processor/__init__.py
datapipelabcustomprocessor/app/node/processor/azure_synapse_gcp_transfer_node.py
datapipelabcustomprocessor-0.1.4.dist-info/METADATA
datapipelabcustomprocessor-0.1.4.dist-info/WHEEL
datapipelabcustomprocessor-0.1.4.dist-info/top_level.txt
datapipelabcustomprocessor-0.1.4.dist-info/RECORD
