Metadata-Version: 2.4
Name: datapipelabcustomprocessor
Version: 0.1.4
Summary: A data pipeline custom processor node.
Requires-Dist: json5
Requires-Dist: loguru
Requires-Dist: azure-storage-blob
Requires-Dist: google-cloud-storage
Requires-Dist: pandas
Dynamic: requires-dist
Dynamic: summary
